plain/worker/CHANGELOG.md
plain/worker/README.md
plain/worker/__init__.py
plain/worker/admin.py
plain/worker/chores.py
plain/worker/cli.py
plain/worker/config.py
plain/worker/default_settings.py
plain/worker/jobs.py
plain/worker/middleware.py
plain/worker/models.py
plain/worker/parameters.py
plain/worker/registry.py
plain/worker/scheduling.py
plain/worker/workers.py
plain/worker/migrations/0001_initial.py
plain/worker/migrations/0002_job_span_id_job_trace_id_jobrequest_span_id_and_more.py
plain/worker/migrations/0003_rename_job_jobprocess_and_more.py
plain/worker/migrations/__init__.py
plain/worker/templates/admin/plainqueue/jobresult_detail.html
plain_worker-0.32.0.dist-info/METADATA
plain_worker-0.32.0.dist-info/WHEEL
plain_worker-0.32.0.dist-info/licenses/LICENSE
plain_worker-0.32.0.dist-info/RECORD
