Metadata-Version: 2.4
Name: plain.worker
Version: 0.32.0
Summary: Process background jobs with a database-driven worker.
Author-email: Dave Gaeddert <dave.gaeddert@dropseed.dev>
License-File: LICENSE
Requires-Python: >=3.13
Requires-Dist: plain-models<1.0.0
Requires-Dist: plain<1.0.0
